st_jsme/__init__.py
st_jsme/frontend/build/asset-manifest.json
st_jsme/frontend/build/bootstrap.min.css
st_jsme/frontend/build/index.html
st_jsme/frontend/build/precache-manifest.aaf86aa453d677732e1207b534dc6876.js
st_jsme/frontend/build/service-worker.js
st_jsme/frontend/build/static/js/2.4ea1358c.chunk.js
st_jsme/frontend/build/static/js/2.4ea1358c.chunk.js.LICENSE.txt
st_jsme/frontend/build/static/js/2.4ea1358c.chunk.js.map
st_jsme/frontend/build/static/js/main.edee5c72.chunk.js
st_jsme/frontend/build/static/js/main.edee5c72.chunk.js.map
st_jsme/frontend/build/static/js/runtime-main.119b752e.js
st_jsme/frontend/build/static/js/runtime-main.119b752e.js.map
st_jsme-0.0.3.dist-info/LICENSE
st_jsme-0.0.3.dist-info/METADATA
st_jsme-0.0.3.dist-info/WHEEL
st_jsme-0.0.3.dist-info/top_level.txt
st_jsme-0.0.3.dist-info/RECORD
