Metadata-Version: 2.1
Name: st-jsme
Version: 0.0.3
Summary: UNKNOWN
Home-page: UNKNOWN
Author: Anton Buch
Author-email: anton.buch@bayer.com
License: UNKNOWN
Platform: UNKNOWN
Requires-Python: >=3.6
License-File: LICENSE
Requires-Dist: streamlit (>=0.63)
